tom_text_toolbox/__init__.py
tom_text_toolbox/common.py
tom_text_toolbox/tom_text_toolbox.py
tom_text_toolbox-0.0.1.dist-info/licenses/LICENSE
tom_text_toolbox-0.0.1.dist-info/METADATA
tom_text_toolbox-0.0.1.dist-info/WHEEL
tom_text_toolbox-0.0.1.dist-info/entry_points.txt
tom_text_toolbox-0.0.1.dist-info/top_level.txt
tom_text_toolbox-0.0.1.dist-info/RECORD
